[
  {
    "name": "St George's, University of London",
    "tier": "Other Universities",
    "overallRank": 65,
    "subjectRank": 1,
    "entryGrades": "ABB",
    "ibGrades": "6-5-5 (16/21)",
    "ucasPoints": "128",
    "typicalOffer": "ABB; one science required",
    "gradProspects": "98%",
    "courseName": "Paramedic Science (BSc)",
    "applicationCode": "B780",
    "sourceUrl": "https://www.sgul.ac.uk/study/undergraduate/paramedic-science-bsc",
    "matchType": "exact",
    "notes": "Verified UCAS 2026 exact title match; HCPC-approved; placements with London Ambulance Service."
  },
  {
    "name": "Coventry University",
    "tier": "Other Universities",
    "overallRank": 70,
    "subjectRank": 2,
    "entryGrades": "BBB",
    "ibGrades": "5-5-5 (15/21)",
    "ucasPoints": "120",
    "typicalOffer": "BBB",
    "gradProspects": "97%",
    "courseName": "Paramedic Science BSc (Hons)",
    "applicationCode": "B780",
    "sourceUrl": "https://www.coventry.ac.uk/course-structure/ug/2026-27/hls/paramedic-science-bsc-hons/",
    "matchType": "exact",
    "notes": "Verified UCAS 2026 exact title match; HCPC-approved."
  },
  {
    "name": "University of Plymouth",
    "tier": "Other Universities",
    "overallRank": 65,
    "subjectRank": 3,
    "entryGrades": "BBC",
    "ibGrades": "5-5-4 (14/21)",
    "ucasPoints": "112",
    "typicalOffer": "BBC",
    "gradProspects": "97%",
    "courseName": "Paramedic Practitioner BSc (Hons)",
    "applicationCode": "B780",
    "sourceUrl": "https://www.plymouth.ac.uk/courses/undergraduate/bsc-paramedic-practitioner",
    "matchType": "exact",
    "notes": "Verified UCAS 2026 exact title match; HCPC-approved."
  },
  {
    "name": "Anglia Ruskin University",
    "tier": "Other Universities",
    "overallRank": 90,
    "subjectRank": 4,
    "entryGrades": "BBC",
    "ibGrades": "5-5-4 (14/21)",
    "ucasPoints": "112",
    "typicalOffer": "BBC",
    "gradProspects": "96%",
    "courseName": "Paramedic Science BSc (Hons)",
    "applicationCode": "B780",
    "sourceUrl": "https://www.aru.ac.uk/study/undergraduate/paramedic-science",
    "matchType": "exact",
    "notes": "Verified UCAS 2026 exact title match; HCPC-approved."
  },
  {
    "name": "University of Cumbria",
    "tier": "Other Universities",
    "overallRank": 100,
    "subjectRank": 5,
    "entryGrades": "BBC",
    "ibGrades": "5-4-4 (13/21)",
    "ucasPoints": "112",
    "typicalOffer": "BBC",
    "gradProspects": "96%",
    "courseName": "Paramedic Practice BSc (Hons)",
    "applicationCode": "B780",
    "sourceUrl": "https://www.cumbria.ac.uk/study/courses/undergraduate/paramedic-practice/",
    "matchType": "exact",
    "notes": "Verified UCAS 2026 exact title match; HCPC-approved."
  },
  {
    "name": "Liverpool John Moores University",
    "tier": "Other Universities",
    "overallRank": 95,
    "subjectRank": 6,
    "entryGrades": "BBC",
    "ibGrades": "5-5-4 (14/21)",
    "ucasPoints": "112",
    "typicalOffer": "BBC",
    "gradProspects": "96%",
    "courseName": "Paramedic Practice BSc (Hons)",
    "applicationCode": "B780",
    "sourceUrl": "https://www.ljmu.ac.uk/study/courses/undergraduates/paramedic-practice-bsc",
    "matchType": "exact",
    "notes": "Verified UCAS 2026 exact title match; HCPC-approved."
  },
  {
    "name": "University of Brighton",
    "tier": "Other Universities",
    "overallRank": 70,
    "subjectRank": 7,
    "entryGrades": "BBC",
    "ibGrades": "5-5-4 (14/21)",
    "ucasPoints": "112",
    "typicalOffer": "BBC",
    "gradProspects": "96%",
    "courseName": "Paramedic Practice BSc Hons",
    "applicationCode": "B780",
    "sourceUrl": "https://www.brighton.ac.uk/courses/study/paramedic-practice-bsc-hons.aspx",
    "matchType": "exact",
    "notes": "Verified UCAS 2026 exact title match; HCPC-approved."
  },
  {
    "name": "University of Hertfordshire",
    "tier": "Other Universities",
    "overallRank": 85,
    "subjectRank": 8,
    "entryGrades": "BBC",
    "ibGrades": "5-5-4 (14/21)",
    "ucasPoints": "112",
    "typicalOffer": "BBC",
    "gradProspects": "95%",
    "courseName": "Paramedic Science BSc (Hons)",
    "applicationCode": "B780",
    "sourceUrl": "https://www.herts.ac.uk/courses/undergraduate/paramedic-science",
    "matchType": "exact",
    "notes": "Verified UCAS 2026 exact title match; HCPC-approved."
  }
]
